MCP23017.py
MCP23S17.py
ssd1306.py
hw101-0.2.0.dist-info/WHEEL
hw101-0.2.0.dist-info/METADATA
hw101-0.2.0.dist-info/RECORD
