Metadata-Version: 2.1
Name: hw101
Version: 0.2.0
Summary: Classes for educational purposes to get started with hardware projects.
Home-page: https://hw101.tbs1.de
Author: Marco Bakera
Author-email: bakera@tbs1.de
Requires-Python: >=3.7,<4.0
Classifier: Programming Language :: Python :: 3
Classifier: Programming Language :: Python :: 3.10
Classifier: Programming Language :: Python :: 3.7
Classifier: Programming Language :: Python :: 3.8
Classifier: Programming Language :: Python :: 3.9
Requires-Dist: smbus (>=1.1.post2,<2.0)
Requires-Dist: spidev (>=3.5,<4.0)
